v2man/__init__.py
v2man/common.py
v2man/errors.py
v2man/freedom.py
v2man/gen.py
v2man/helper.py
v2man/man.py
v2man/stream.py
v2man/vmess.py
v2man/v2grpc/__init__.py
v2man/v2grpc/proxyman_pb2_grpc.py
v2man/v2grpc/stats_pb2_grpc.py
v2man/v2grpc/v2ray/__init__.py
v2man/v2grpc/v2ray/com/__init__.py
v2man/v2grpc/v2ray/com/core/__init__.py
v2man/v2grpc/v2ray/com/core/config_pb2.py
v2man/v2grpc/v2ray/com/core/app/__init__.py
v2man/v2grpc/v2ray/com/core/app/commander/__init__.py
v2man/v2grpc/v2ray/com/core/app/commander/config_pb2.py
v2man/v2grpc/v2ray/com/core/app/dispatcher/__init__.py
v2man/v2grpc/v2ray/com/core/app/dispatcher/config_pb2.py
v2man/v2grpc/v2ray/com/core/app/dns/__init__.py
v2man/v2grpc/v2ray/com/core/app/dns/config_pb2.py
v2man/v2grpc/v2ray/com/core/app/log/__init__.py
v2man/v2grpc/v2ray/com/core/app/log/config_pb2.py
v2man/v2grpc/v2ray/com/core/app/log/command/__init__.py
v2man/v2grpc/v2ray/com/core/app/log/command/config_pb2.py
v2man/v2grpc/v2ray/com/core/app/policy/__init__.py
v2man/v2grpc/v2ray/com/core/app/policy/config_pb2.py
v2man/v2grpc/v2ray/com/core/app/proxyman/__init__.py
v2man/v2grpc/v2ray/com/core/app/proxyman/config_pb2.py
v2man/v2grpc/v2ray/com/core/app/proxyman/command/__init__.py
v2man/v2grpc/v2ray/com/core/app/proxyman/command/command_pb2.py
v2man/v2grpc/v2ray/com/core/app/reverse/__init__.py
v2man/v2grpc/v2ray/com/core/app/reverse/config_pb2.py
v2man/v2grpc/v2ray/com/core/app/router/__init__.py
v2man/v2grpc/v2ray/com/core/app/router/config_pb2.py
v2man/v2grpc/v2ray/com/core/app/stats/__init__.py
v2man/v2grpc/v2ray/com/core/app/stats/config_pb2.py
v2man/v2grpc/v2ray/com/core/app/stats/command/__init__.py
v2man/v2grpc/v2ray/com/core/app/stats/command/command_pb2.py
v2man/v2grpc/v2ray/com/core/common/__init__.py
v2man/v2grpc/v2ray/com/core/common/log/__init__.py
v2man/v2grpc/v2ray/com/core/common/log/log_pb2.py
v2man/v2grpc/v2ray/com/core/common/net/__init__.py
v2man/v2grpc/v2ray/com/core/common/net/address_pb2.py
v2man-0.1.1.dist-info/License
v2man-0.1.1.dist-info/METADATA
v2man-0.1.1.dist-info/WHEEL
v2man-0.1.1.dist-info/entry_points.txt
v2man-0.1.1.dist-info/top_level.txt
v2man-0.1.1.dist-info/RECORD
