Metadata-Version: 2.1
Name: v2man
Version: 0.1.1
Summary: A v2ray python client based on v2ray gRPC API
Home-page: UNKNOWN
Author: Unixeno
Author-email: li139793780@gmail.com
License: MIT Licence
Platform: UNKNOWN
Classifier: Development Status :: 3 - Alpha
Classifier: Intended Audience :: Developers
Classifier: License :: OSI Approved :: MIT License
Classifier: Programming Language :: Python :: 3
Classifier: Programming Language :: Python :: 3.6
Classifier: Programming Language :: Python :: 3.7
Classifier: Programming Language :: Python :: 3.8
Requires-Python: >=3.6
License-File: License
Requires-Dist: grpcio (==1.42.0)
Requires-Dist: grpcio-tools (==1.42.0)
